coaxial_pip_packager/__init__.py
coaxial_pip_packager/__main__.py
coaxial_pip_packager/packager.py
coaxial_pip_packager-1.0.0.dist-info/licenses/LICENSE
coaxial_pip_packager-1.0.0.dist-info/METADATA
coaxial_pip_packager-1.0.0.dist-info/WHEEL
coaxial_pip_packager-1.0.0.dist-info/entry_points.txt
coaxial_pip_packager-1.0.0.dist-info/top_level.txt
coaxial_pip_packager-1.0.0.dist-info/RECORD
