Metadata-Version: 2.4
Name: coaxial-pip-packager
Version: 1.0.0
Summary: Automate packaging and releasing Python packages to PyPI with version management and git integration
Author-email: Coaxial <coaxial@example.com>
License: MIT
Project-URL: Homepage, https://github.com/coaxialdolor/coaxial-pip-packager
Project-URL: Issues, https://github.com/coaxialdolor/coaxial-pip-packager/issues
Keywords: packaging,pypi,automation,versioning,git
Classifier: Development Status :: 4 - Beta
Classifier: Environment :: Console
Classifier: Intended Audience :: Developers
Classifier: License :: OSI Approved :: MIT License
Classifier: Programming Language :: Python :: 3
Classifier: Programming Language :: Python :: 3.7
Classifier: Programming Language :: Python :: 3.8
Classifier: Programming Language :: Python :: 3.9
Classifier: Programming Language :: Python :: 3.10
Classifier: Programming Language :: Python :: 3.11
Classifier: Topic :: Software Development :: Build Tools
Classifier: Topic :: Software Development :: Libraries :: Python Modules
Requires-Python: >=3.7
License-File: LICENSE
Requires-Dist: colorama
Requires-Dist: toml
Requires-Dist: build
Requires-Dist: twine
Dynamic: license-file
